<?xml version="1.0" encoding="utf-8"?>
<TextureAtlas imagePath="Evil_BF_Guitar_2.png">
	<!-- Created with Adobe Animate version 21.0.9.42677 -->
	<!-- http://www.adobe.com/products/animate.html -->
	<SubTexture name="full animation 10000" x="0" y="0" width="587" height="607" frameX="-11" frameY="0" frameWidth="598" frameHeight="612"/>
	<SubTexture name="full animation 10001" x="0" y="0" width="587" height="607" frameX="-11" frameY="0" frameWidth="598" frameHeight="612"/>
	<SubTexture name="full animation 10002" x="587" y="0" width="587" height="607" frameX="-11" frameY="0" frameWidth="598" frameHeight="612"/>
	<SubTexture name="full animation 10003" x="587" y="0" width="587" height="607" frameX="-11" frameY="0" frameWidth="598" frameHeight="612"/>
	<SubTexture name="full animation 10004" x="0" y="0" width="587" height="607" frameX="-11" frameY="0" frameWidth="598" frameHeight="612"/>
	<SubTexture name="full animation 10005" x="0" y="0" width="587" height="607" frameX="-11" frameY="0" frameWidth="598" frameHeight="612"/>
	<SubTexture name="full animation 10006" x="1174" y="0" width="587" height="607" frameX="-11" frameY="0" frameWidth="598" frameHeight="612"/>
	<SubTexture name="full animation 10007" x="1174" y="0" width="587" height="607" frameX="-11" frameY="0" frameWidth="598" frameHeight="612"/>
	<SubTexture name="full animation 10008" x="587" y="0" width="587" height="607" frameX="-11" frameY="0" frameWidth="598" frameHeight="612"/>
	<SubTexture name="full animation 10009" x="587" y="0" width="587" height="607" frameX="-11" frameY="0" frameWidth="598" frameHeight="612"/>
	<SubTexture name="full animation 10010" x="0" y="0" width="587" height="607" frameX="-11" frameY="0" frameWidth="598" frameHeight="612"/>
	<SubTexture name="full animation 10011" x="0" y="0" width="587" height="607" frameX="-11" frameY="0" frameWidth="598" frameHeight="612"/>
	<SubTexture name="full animation 10012" x="587" y="0" width="587" height="607" frameX="-11" frameY="0" frameWidth="598" frameHeight="612"/>
	<SubTexture name="full animation 10013" x="587" y="0" width="587" height="607" frameX="-11" frameY="0" frameWidth="598" frameHeight="612"/>
	<SubTexture name="full animation 10014" x="0" y="0" width="587" height="607" frameX="-11" frameY="0" frameWidth="598" frameHeight="612"/>
	<SubTexture name="full animation 10015" x="0" y="0" width="587" height="607" frameX="-11" frameY="0" frameWidth="598" frameHeight="612"/>
	<SubTexture name="full animation 10016" x="1174" y="0" width="587" height="607" frameX="-11" frameY="0" frameWidth="598" frameHeight="612"/>
	<SubTexture name="full animation 10017" x="0" y="607" width="490" height="591" frameX="-73" frameY="-21" frameWidth="598" frameHeight="612"/>
	<SubTexture name="full animation 10018" x="0" y="607" width="490" height="591" frameX="-73" frameY="-21" frameWidth="598" frameHeight="612"/>
	<SubTexture name="full animation 10019" x="490" y="607" width="490" height="591" frameX="-73" frameY="-21" frameWidth="598" frameHeight="612"/>
	<SubTexture name="full animation 10020" x="980" y="607" width="471" height="587" frameX="-37" frameY="-16" frameWidth="598" frameHeight="612"/>
	<SubTexture name="full animation 10021" x="980" y="607" width="471" height="587" frameX="-37" frameY="-16" frameWidth="598" frameHeight="612"/>
	<SubTexture name="full animation 10022" x="980" y="607" width="471" height="587" frameX="-37" frameY="-16" frameWidth="598" frameHeight="612"/>
	<SubTexture name="full animation 10023" x="980" y="607" width="471" height="587" frameX="-37" frameY="-16" frameWidth="598" frameHeight="612"/>
	<SubTexture name="full animation 10024" x="980" y="607" width="471" height="587" frameX="-37" frameY="-16" frameWidth="598" frameHeight="612"/>
	<SubTexture name="full animation 10025" x="980" y="607" width="471" height="587" frameX="-37" frameY="-16" frameWidth="598" frameHeight="612"/>
	<SubTexture name="full animation 10026" x="980" y="607" width="471" height="587" frameX="-37" frameY="-16" frameWidth="598" frameHeight="612"/>
	<SubTexture name="full animation 10027" x="980" y="607" width="471" height="587" frameX="-37" frameY="-16" frameWidth="598" frameHeight="612"/>
	<SubTexture name="full animation 10028" x="980" y="607" width="471" height="587" frameX="-37" frameY="-16" frameWidth="598" frameHeight="612"/>
	<SubTexture name="full animation 10029" x="980" y="607" width="471" height="587" frameX="-37" frameY="-16" frameWidth="598" frameHeight="612"/>
	<SubTexture name="full animation 10030" x="980" y="607" width="471" height="587" frameX="-37" frameY="-16" frameWidth="598" frameHeight="612"/>
	<SubTexture name="full animation 10031" x="1451" y="607" width="586" height="610" frameX="0" frameY="0" frameWidth="598" frameHeight="612"/>
	<SubTexture name="full animation 10032" x="1451" y="607" width="586" height="610" frameX="0" frameY="0" frameWidth="598" frameHeight="612"/>
	<SubTexture name="full animation 10033" x="0" y="1217" width="586" height="610" frameX="0" frameY="0" frameWidth="598" frameHeight="612"/>
	<SubTexture name="full animation 10034" x="0" y="1217" width="586" height="610" frameX="0" frameY="0" frameWidth="598" frameHeight="612"/>
	<SubTexture name="full animation 10035" x="1451" y="607" width="586" height="610" frameX="0" frameY="0" frameWidth="598" frameHeight="612"/>
	<SubTexture name="full animation 10036" x="1451" y="607" width="586" height="610" frameX="0" frameY="0" frameWidth="598" frameHeight="612"/>
	<SubTexture name="full animation 10037" x="586" y="1217" width="586" height="610" frameX="0" frameY="0" frameWidth="598" frameHeight="612"/>
	<SubTexture name="full animation 10038" x="586" y="1217" width="586" height="610" frameX="0" frameY="0" frameWidth="598" frameHeight="612"/>
	<SubTexture name="full animation 10039" x="0" y="1217" width="586" height="610" frameX="0" frameY="0" frameWidth="598" frameHeight="612"/>
	<SubTexture name="full animation 10040" x="0" y="1217" width="586" height="610" frameX="0" frameY="0" frameWidth="598" frameHeight="612"/>
	<SubTexture name="full animation 10041" x="1451" y="607" width="586" height="610" frameX="0" frameY="0" frameWidth="598" frameHeight="612"/>
	<SubTexture name="full animation 10042" x="1451" y="607" width="586" height="610" frameX="0" frameY="0" frameWidth="598" frameHeight="612"/>
	<SubTexture name="full animation 10043" x="0" y="1217" width="586" height="610" frameX="0" frameY="0" frameWidth="598" frameHeight="612"/>
	<SubTexture name="full animation 10044" x="0" y="1217" width="586" height="610" frameX="0" frameY="0" frameWidth="598" frameHeight="612"/>
	<SubTexture name="full animation 10045" x="1451" y="607" width="586" height="610" frameX="0" frameY="0" frameWidth="598" frameHeight="612"/>
	<SubTexture name="full animation 10046" x="1451" y="607" width="586" height="610" frameX="0" frameY="0" frameWidth="598" frameHeight="612"/>
	<SubTexture name="full animation 10047" x="586" y="1217" width="586" height="610" frameX="0" frameY="0" frameWidth="598" frameHeight="612"/>
	<SubTexture name="full animation 10048" x="586" y="1217" width="586" height="610" frameX="0" frameY="0" frameWidth="598" frameHeight="612"/>
	<SubTexture name="full animation 10049" x="0" y="1217" width="586" height="610" frameX="0" frameY="0" frameWidth="598" frameHeight="612"/>
	<SubTexture name="full animation 10050" x="0" y="1217" width="586" height="610" frameX="0" frameY="0" frameWidth="598" frameHeight="612"/>
	<SubTexture name="full animation 10051" x="1451" y="607" width="586" height="610" frameX="0" frameY="0" frameWidth="598" frameHeight="612"/>
	<SubTexture name="full animation 10052" x="1451" y="607" width="586" height="610" frameX="0" frameY="0" frameWidth="598" frameHeight="612"/>
	<SubTexture name="full animation 10053" x="0" y="1217" width="586" height="610" frameX="0" frameY="0" frameWidth="598" frameHeight="612"/>
	<SubTexture name="full animation 10054" x="0" y="1217" width="586" height="610" frameX="0" frameY="0" frameWidth="598" frameHeight="612"/>
	<SubTexture name="full animation 10055" x="1451" y="607" width="586" height="610" frameX="0" frameY="0" frameWidth="598" frameHeight="612"/>
	<SubTexture name="full animation 10056" x="1451" y="607" width="586" height="610" frameX="0" frameY="0" frameWidth="598" frameHeight="612"/>
	<SubTexture name="full animation 10057" x="586" y="1217" width="586" height="610" frameX="0" frameY="0" frameWidth="598" frameHeight="612"/>
	<SubTexture name="full animation 10058" x="586" y="1217" width="586" height="610" frameX="0" frameY="0" frameWidth="598" frameHeight="612"/>
	<SubTexture name="full animation 10059" x="0" y="1217" width="586" height="610" frameX="0" frameY="0" frameWidth="598" frameHeight="612"/>
	<SubTexture name="full animation 10060" x="0" y="1217" width="586" height="610" frameX="0" frameY="0" frameWidth="598" frameHeight="612"/>
	<SubTexture name="full animation 10061" x="1451" y="607" width="586" height="610" frameX="0" frameY="0" frameWidth="598" frameHeight="612"/>
	<SubTexture name="full animation 10062" x="1451" y="607" width="586" height="610" frameX="0" frameY="0" frameWidth="598" frameHeight="612"/>
	<SubTexture name="full animation 10063" x="0" y="1217" width="586" height="610" frameX="0" frameY="0" frameWidth="598" frameHeight="612"/>
	<SubTexture name="full animation 10064" x="0" y="1217" width="586" height="610" frameX="0" frameY="0" frameWidth="598" frameHeight="612"/>
	<SubTexture name="full animation 10065" x="1451" y="607" width="586" height="610" frameX="0" frameY="0" frameWidth="598" frameHeight="612"/>
	<SubTexture name="full animation 10066" x="1451" y="607" width="586" height="610" frameX="0" frameY="0" frameWidth="598" frameHeight="612"/>
	<SubTexture name="full animation 10067" x="586" y="1217" width="586" height="610" frameX="0" frameY="0" frameWidth="598" frameHeight="612"/>
	<SubTexture name="full animation 10068" x="586" y="1217" width="586" height="610" frameX="0" frameY="0" frameWidth="598" frameHeight="612"/>
	<SubTexture name="full animation 10069" x="0" y="1217" width="586" height="610" frameX="0" frameY="0" frameWidth="598" frameHeight="612"/>
	<SubTexture name="full animation 10070" x="0" y="1217" width="586" height="610" frameX="0" frameY="0" frameWidth="598" frameHeight="612"/>
	<SubTexture name="full animation 10071" x="1451" y="607" width="586" height="610" frameX="0" frameY="0" frameWidth="598" frameHeight="612"/>
	<SubTexture name="full animation 10072" x="1451" y="607" width="586" height="610" frameX="0" frameY="0" frameWidth="598" frameHeight="612"/>
	<SubTexture name="full animation 10073" x="0" y="1217" width="586" height="610" frameX="0" frameY="0" frameWidth="598" frameHeight="612"/>
	<SubTexture name="full animation 10074" x="0" y="1217" width="586" height="610" frameX="0" frameY="0" frameWidth="598" frameHeight="612"/>
	<SubTexture name="full animation 10075" x="1451" y="607" width="586" height="610" frameX="0" frameY="0" frameWidth="598" frameHeight="612"/>
	<SubTexture name="full animation 10076" x="1451" y="607" width="586" height="610" frameX="0" frameY="0" frameWidth="598" frameHeight="612"/>
	<SubTexture name="full animation 10077" x="586" y="1217" width="586" height="610" frameX="0" frameY="0" frameWidth="598" frameHeight="612"/>
	<SubTexture name="full animation 10078" x="586" y="1217" width="586" height="610" frameX="0" frameY="0" frameWidth="598" frameHeight="612"/>
	<SubTexture name="full animation 10079" x="0" y="1217" width="586" height="610" frameX="0" frameY="0" frameWidth="598" frameHeight="612"/>
	<SubTexture name="full animation 10080" x="0" y="1217" width="586" height="610" frameX="0" frameY="0" frameWidth="598" frameHeight="612"/>
	<SubTexture name="full animation 10081" x="1451" y="607" width="586" height="610" frameX="0" frameY="0" frameWidth="598" frameHeight="612"/>
	<SubTexture name="full animation 10082" x="1451" y="607" width="586" height="610" frameX="0" frameY="0" frameWidth="598" frameHeight="612"/>
</TextureAtlas>
